setup.py
FoxLogo/__init__.py
FoxLogo/logo.py
FoxLogo.egg-info/PKG-INFO
FoxLogo.egg-info/SOURCES.txt
FoxLogo.egg-info/dependency_links.txt
FoxLogo.egg-info/top_level.txt