Metadata-Version: 2.1
Name: FoxLogo
Version: 0.0.2
Summary: SnowFox工作室发出的SnowFox的logo系列
Home-page: https://github.com/
Author: haowen zhang
Author-email: 806670753@qq.com
License: UNKNOWN
Platform: UNKNOWN
Classifier: Programming Language :: Python :: 3
Classifier: License :: OSI Approved :: MIT License
Classifier: Operating System :: OS Independent
